lru/__init__.py
lru_od-0.0.1.dist-info/LICENSE
lru_od-0.0.1.dist-info/METADATA
lru_od-0.0.1.dist-info/WHEEL
lru_od-0.0.1.dist-info/top_level.txt
lru_od-0.0.1.dist-info/RECORD
